adk_mongodb_session/__init__.py
adk_mongodb_session/mongodb/__init__.py
adk_mongodb_session/mongodb/sessions/__init__.py
adk_mongodb_session/mongodb/sessions/mongodb_session.py
adk_mongodb_session/mongodb/sessions/mongodb_session_service.py
adk_mongodb_session-1.0.9.dist-info/licenses/LICENSE
adk_mongodb_session-1.0.9.dist-info/METADATA
adk_mongodb_session-1.0.9.dist-info/WHEEL
adk_mongodb_session-1.0.9.dist-info/top_level.txt
adk_mongodb_session-1.0.9.dist-info/RECORD
