Metadata-Version: 2.4
Name: adk-mongodb-session
Version: 1.0.9
Summary: A project to integrate together Agent Development Kit (ADK) with MongoDB session management as backend storage.
Classifier: Programming Language :: Python :: 3
Classifier: License :: OSI Approved :: MIT License
Classifier: Operating System :: OS Independent
Requires-Python: >=3.11
License-File: LICENSE
Requires-Dist: pymongo<5.0,>=4.7
Requires-Dist: google-adk>=1.15.1
Provides-Extra: test
Requires-Dist: mongomock~=4.1.2; extra == "test"
Dynamic: license-file
